copepodTCR/__init__.py
copepodTCR/functions.py
copepodtcr-0.5.1.dist-info/METADATA
copepodtcr-0.5.1.dist-info/WHEEL
copepodtcr-0.5.1.dist-info/licenses/LICENSE
copepodtcr-0.5.1.dist-info/RECORD
