Metadata-Version: 2.4
Name: copepodTCR
Version: 0.5.1
Summary: COmbinatorial PEptide POoling for TCR specificity
Project-URL: Homepage, https://copepodtcr.readthedocs.io/en/latest/index.html
Project-URL: Bug Tracker, https://github.com/meyer-lab-cshl/copepodTCR/issues
Author-email: Vasilisa Kovaleva <vasilisa.kovaliova@gmail.com>
License-File: LICENSE
Classifier: License :: OSI Approved :: BSD License
Classifier: Operating System :: OS Independent
Classifier: Programming Language :: Python :: 3
Requires-Python: >=3.7
Requires-Dist: arviz>=0.16.1
Requires-Dist: codepub>=2.3
Requires-Dist: matplotlib>=3.10.5
Requires-Dist: numpy>=1.23.5
Requires-Dist: pandas>=1.5.3
Requires-Dist: plotly>=6.2.0
Requires-Dist: pymc>=5.9.2
Requires-Dist: seaborn>=0.13.2
Requires-Dist: trimesh>=4.7.1
